AUTHORS
CHANGELOG
INSTALL
LICENSE
README
setup.cfg
setup.py
byCycle/__init__.py
byCycle/model/__init__.py
byCycle/model/address.py
byCycle/model/compass.py
byCycle/model/db.py
byCycle/model/geocode.py
byCycle/model/glineenc.py
byCycle/model/point.py
byCycle/model/region.py
byCycle/model/regions.py
byCycle/model/route.py
byCycle/model/states.py
byCycle/model/sttypes.py
byCycle/model/tmode.py
byCycle/model/data/__init__.py
byCycle/model/data/integrator.py
byCycle/model/data/schema.sql
byCycle/model/data/sqltypes.py
byCycle/model/entities/__init__.py
byCycle/model/entities/base.py
byCycle/model/entities/public.py
byCycle/model/entities/util.py
byCycle/model/milwaukeewi/__init__.py
byCycle/model/milwaukeewi/bicycle.py
byCycle/model/milwaukeewi/hours.xls
byCycle/model/milwaukeewi/data/__init__.py
byCycle/model/milwaukeewi/data/integrator.py
byCycle/model/milwaukeewi/data/schema.sql
byCycle/model/milwaukeewi/data/shp2sql.py
byCycle/model/portlandor/__init__.py
byCycle/model/portlandor/bicycle.py
byCycle/model/portlandor/data/__init__.py
byCycle/model/portlandor/data/cities.py
byCycle/model/portlandor/data/integrator.py
byCycle/model/portlandor/data/schema.sql
byCycle/scripts/__init__.py
byCycle/scripts/bycycle.py
byCycle/scripts/integrate.py
byCycle/scripts/matrix.py
byCycle/scripts/test_bycycle.py
byCycle/scripts/upgrade_data.sh
byCycle/services/__init__.py
byCycle/services/exceptions.py
byCycle/services/geocode.py
byCycle/services/identify.py
byCycle/services/normaddr.py
byCycle/services/route.py
byCycle/util/__init__.py
byCycle/util/gis.py
byCycle/util/meter.py
byCycleCore.egg-info/PKG-INFO
byCycleCore.egg-info/SOURCES.txt
byCycleCore.egg-info/dependency_links.txt
byCycleCore.egg-info/not-zip-safe
byCycleCore.egg-info/requires.txt
byCycleCore.egg-info/top_level.txt
config/httpd.conf
tests/test_gis.py
tests/test_model/test_address.py
tests/test_services/test_geocode.py
tests/test_services/test_normaddr.py
tests/test_services/test_route.py