Metadata-Version: 1.0
Name: byCycleCore
Version: 0.4a0.dev-r1054
Summary: byCycle Core Services
Home-page: http://bycycle.org/
Author: Wyatt L Baldwin, byCycle.org
Author-email: wyatt@byCycle.org
License: Free For Home Use
Download-URL: http://guest:guest@code.bycycle.org/core/trunk#egg=byCycleCore-dev
Keywords: bicycle bike cycyle trip planner route finder
Platform: UNKNOWN
Classifier: Development Status :: 3 - Alpha
Classifier: Environment :: Console
Classifier: Intended Audience :: Developers
Classifier: License :: OSI Approved :: GNU General Public License (GPL)
Classifier: Natural Language :: English
Classifier: Operating System :: POSIX :: Linux
Classifier: Programming Language :: Python
Classifier: Topic :: Education
Classifier: Topic :: Scientific/Engineering :: GIS
